[
  {
    "train_lr": 0.00010000000000002535,
    "train_class_error": 28.001248359520083,
    "train_loss": 23.59234986746133,
    "train_loss_ce_dn": 0.12569245258977818,
    "train_loss_bbox_dn": 0.5109731274469655,
    "train_loss_giou_dn": 0.4951781517975639,
    "train_loss_ce": 0.5754197387052469,
    "train_loss_bbox": 0.8524886956096036,
    "train_loss_giou": 0.9080366704619849,
    "train_loss_ce_0": 0.607996664901546,
    "train_loss_bbox_0": 0.8811093099926224,
    "train_loss_giou_0": 0.9209342947517722,
    "train_loss_ce_dn_0": 0.13197483738331822,
    "train_loss_bbox_dn_0": 0.5114245668595504,
    "train_loss_giou_dn_0": 0.49505494551103707,
    "train_loss_ce_1": 0.5959900115342399,
    "train_loss_bbox_1": 0.8603405293420555,
    "train_loss_giou_1": 0.9126230438275987,
    "train_loss_ce_dn_1": 0.12790422434878715,
    "train_loss_bbox_dn_1": 0.5107366139438476,
    "train_loss_giou_dn_1": 0.49467473436976833,
    "train_loss_ce_2": 0.586997526534001,
    "train_loss_bbox_2": 0.854200814546858,
    "train_loss_giou_2": 0.9091217590419962,
    "train_loss_ce_dn_2": 0.12455457115499904,
    "train_loss_bbox_dn_2": 0.5105027715735412,
    "train_loss_giou_dn_2": 0.49471361949146847,
    "train_loss_ce_3": 0.5809137413758605,
    "train_loss_bbox_3": 0.8526627908424681,
    "train_loss_giou_3": 0.9082061131480899,
    "train_loss_ce_dn_3": 0.12357821910982442,
    "train_loss_bbox_dn_3": 0.5105751173593265,
    "train_loss_giou_dn_3": 0.4947345663766963,
    "train_loss_ce_4": 0.5776573950383146,
    "train_loss_bbox_4": 0.8525036248746326,
    "train_loss_giou_4": 0.9082055618113792,
    "train_loss_ce_dn_4": 0.1239334705791647,
    "train_loss_bbox_dn_4": 0.5106127056063681,
    "train_loss_giou_dn_4": 0.4951160448833622,
    "train_loss_ce_interm": 0.773566128464191,
    "train_loss_bbox_interm": 0.9335980364549089,
    "train_loss_giou_interm": 0.9478426956819751,
    "train_loss_ce_dn_unscaled": 0.12569245258977818,
    "train_loss_bbox_dn_unscaled": 0.10219462543274299,
    "train_loss_giou_dn_unscaled": 0.24758907589878196,
    "train_loss_xy_dn_unscaled": 0.0338230887473558,
    "train_loss_hw_dn_unscaled": 0.068371536746194,
    "train_cardinality_error_dn_unscaled": 68.53369984891724,
    "train_loss_ce_unscaled": 0.5754197387052469,
    "train_class_error_unscaled": 28.001248359520083,
    "train_loss_bbox_unscaled": 0.17049773901279477,
    "train_loss_giou_unscaled": 0.45401833523099244,
    "train_loss_xy_unscaled": 0.06365488788852647,
    "train_loss_hw_unscaled": 0.10684285110152072,
    "train_cardinality_error_unscaled": 231.56681215376867,
    "train_loss_ce_0_unscaled": 0.607996664901546,
    "train_loss_bbox_0_unscaled": 0.17622186190112413,
    "train_loss_giou_0_unscaled": 0.4604671473758861,
    "train_loss_xy_0_unscaled": 0.06594773661681376,
    "train_loss_hw_0_unscaled": 0.11027412524686672,
    "train_cardinality_error_0_unscaled": 236.4562069833809,
    "train_loss_ce_dn_0_unscaled": 0.13197483738331822,
    "train_loss_bbox_dn_0_unscaled": 0.10228491330460143,
    "train_loss_giou_dn_0_unscaled": 0.24752747275551854,
    "train_loss_xy_dn_0_unscaled": 0.03381624359125033,
    "train_loss_hw_dn_0_unscaled": 0.06846866977882374,
    "train_cardinality_error_dn_0_unscaled": 67.78909266409266,
    "train_loss_ce_1_unscaled": 0.5959900115342399,
    "train_loss_bbox_1_unscaled": 0.1720681057133522,
    "train_loss_giou_1_unscaled": 0.45631152191379937,
    "train_loss_xy_1_unscaled": 0.06442312716999052,
    "train_loss_hw_1_unscaled": 0.10764497852757128,
    "train_cardinality_error_1_unscaled": 235.94546332046332,
    "train_loss_ce_dn_1_unscaled": 0.12790422434878715,
    "train_loss_bbox_dn_1_unscaled": 0.10214732275023151,
    "train_loss_giou_dn_1_unscaled": 0.24733736718488417,
    "train_loss_xy_dn_1_unscaled": 0.03380161074546114,
    "train_loss_hw_dn_1_unscaled": 0.0683457120514772,
    "train_cardinality_error_dn_1_unscaled": 70.8160147725365,
    "train_loss_ce_2_unscaled": 0.586997526534001,
    "train_loss_bbox_2_unscaled": 0.17084016279199088,
    "train_loss_giou_2_unscaled": 0.4545608795209981,
    "train_loss_xy_2_unscaled": 0.06389137047832459,
    "train_loss_hw_2_unscaled": 0.1069487923276588,
    "train_cardinality_error_2_unscaled": 229.63698170219908,
    "train_loss_ce_dn_2_unscaled": 0.12455457115499904,
    "train_loss_bbox_dn_2_unscaled": 0.10210055426200572,
    "train_loss_giou_dn_2_unscaled": 0.24735680974573424,
    "train_loss_xy_dn_2_unscaled": 0.03380434571559228,
    "train_loss_hw_dn_2_unscaled": 0.06829620846082658,
    "train_cardinality_error_dn_2_unscaled": 69.20347910021823,
    "train_loss_ce_3_unscaled": 0.5809137413758605,
    "train_loss_bbox_3_unscaled": 0.17053255804141976,
    "train_loss_giou_3_unscaled": 0.4541030565740449,
    "train_loss_xy_3_unscaled": 0.06363743474735227,
    "train_loss_hw_3_unscaled": 0.10689512330288121,
    "train_cardinality_error_3_unscaled": 230.9999370488501,
    "train_loss_ce_dn_3_unscaled": 0.12357821910982442,
    "train_loss_bbox_dn_3_unscaled": 0.10211502340392738,
    "train_loss_giou_dn_3_unscaled": 0.24736728318834816,
    "train_loss_xy_dn_3_unscaled": 0.03380469550386516,
    "train_loss_hw_dn_3_unscaled": 0.06831032795496718,
    "train_cardinality_error_dn_3_unscaled": 69.62569246264898,
    "train_loss_ce_4_unscaled": 0.5776573950383146,
    "train_loss_bbox_4_unscaled": 0.17050072494264212,
    "train_loss_giou_4_unscaled": 0.4541027809056896,
    "train_loss_xy_4_unscaled": 0.06369250330454343,
    "train_loss_hw_4_unscaled": 0.10680822158832368,
    "train_cardinality_error_4_unscaled": 225.46986738291085,
    "train_loss_ce_dn_4_unscaled": 0.1239334705791647,
    "train_loss_bbox_dn_4_unscaled": 0.10212254104909105,
    "train_loss_giou_dn_4_unscaled": 0.2475580224416811,
    "train_loss_xy_dn_4_unscaled": 0.033813882618780995,
    "train_loss_hw_dn_4_unscaled": 0.06830865842959674,
    "train_cardinality_error_dn_4_unscaled": 67.80296290078898,
    "train_loss_ce_interm_unscaled": 0.773566128464191,
    "train_loss_bbox_interm_unscaled": 0.1867196072447674,
    "train_loss_giou_interm_unscaled": 0.47392134784098755,
    "train_loss_xy_interm_unscaled": 0.07061033054422702,
    "train_loss_hw_interm_unscaled": 0.11610927676635989,
    "train_cardinality_error_interm_unscaled": 246.74779670975323,
    "test_class_error": 45.70331326905834,
    "test_loss": 10.942452023172468,
    "test_loss_bbox_dn": 0.0,
    "test_loss_giou_dn": 0.0,
    "test_loss_ce_dn": 0.0,
    "test_loss_ce": 0.3947939158352205,
    "test_loss_bbox": 0.5030929978546441,
    "test_loss_giou": 0.6118575988417719,
    "test_loss_ce_0": 0.42747228030979323,
    "test_loss_bbox_0": 0.5135425027390678,
    "test_loss_giou_0": 0.6180863155409116,
    "test_loss_bbox_dn_0": 0.0,
    "test_loss_giou_dn_0": 0.0,
    "test_loss_ce_dn_0": 0.0,
    "test_loss_ce_1": 0.4061971428630222,
    "test_loss_bbox_1": 0.5110038688906454,
    "test_loss_giou_1": 0.6176858832832774,
    "test_loss_bbox_dn_1": 0.0,
    "test_loss_giou_dn_1": 0.0,
    "test_loss_ce_dn_1": 0.0,
    "test_loss_ce_2": 0.39808743033432703,
    "test_loss_bbox_2": 0.5072946049702178,
    "test_loss_giou_2": 0.616203283383706,
    "test_loss_bbox_dn_2": 0.0,
    "test_loss_giou_dn_2": 0.0,
    "test_loss_ce_dn_2": 0.0,
    "test_loss_ce_3": 0.4027965914976836,
    "test_loss_bbox_3": 0.5037817153315153,
    "test_loss_giou_3": 0.6134236627942855,
    "test_loss_bbox_dn_3": 0.0,
    "test_loss_giou_dn_3": 0.0,
    "test_loss_ce_dn_3": 0.0,
    "test_loss_ce_4": 0.3977412321928462,
    "test_loss_bbox_4": 0.5033507984977006,
    "test_loss_giou_4": 0.6120008640396997,
    "test_loss_bbox_dn_4": 0.0,
    "test_loss_giou_dn_4": 0.0,
    "test_loss_ce_dn_4": 0.0,
    "test_loss_ce_interm": 0.5959718101471598,
    "test_loss_bbox_interm": 0.5526880343949735,
    "test_loss_giou_interm": 0.6353795055608387,
    "test_loss_bbox_dn_unscaled": 0.0,
    "test_loss_giou_dn_unscaled": 0.0,
    "test_loss_ce_dn_unscaled": 0.0,
    "test_loss_xy_dn_unscaled": 0.0,
    "test_loss_hw_dn_unscaled": 0.0,
    "test_cardinality_error_dn_unscaled": 0.0,
    "test_loss_ce_unscaled": 0.3947939158352205,
    "test_class_error_unscaled": 45.70331326905834,
    "test_loss_bbox_unscaled": 0.10061859954986926,
    "test_loss_giou_unscaled": 0.30592879942088597,
    "test_loss_xy_unscaled": 0.037900881568069,
    "test_loss_hw_unscaled": 0.06271771796424086,
    "test_cardinality_error_unscaled": 333.97031790997795,
    "test_loss_ce_0_unscaled": 0.42747228030979323,
    "test_loss_bbox_0_unscaled": 0.10270850049518811,
    "test_loss_giou_0_unscaled": 0.3090431577704558,
    "test_loss_xy_0_unscaled": 0.03873565600824982,
    "test_loss_hw_0_unscaled": 0.06397284447166542,
    "test_cardinality_error_0_unscaled": 276.57418948693737,
    "test_loss_bbox_dn_0_unscaled": 0.0,
    "test_loss_giou_dn_0_unscaled": 0.0,
    "test_loss_ce_dn_0_unscaled": 0.0,
    "test_loss_xy_dn_0_unscaled": 0.0,
    "test_loss_hw_dn_0_unscaled": 0.0,
    "test_cardinality_error_dn_0_unscaled": 0.0,
    "test_loss_ce_1_unscaled": 0.4061971428630222,
    "test_loss_bbox_1_unscaled": 0.1022007737105884,
    "test_loss_giou_1_unscaled": 0.3088429416416387,
    "test_loss_xy_1_unscaled": 0.038577161587336206,
    "test_loss_hw_1_unscaled": 0.06362361214034257,
    "test_cardinality_error_1_unscaled": 273.3329241422726,
    "test_loss_bbox_dn_1_unscaled": 0.0,
    "test_loss_giou_dn_1_unscaled": 0.0,
    "test_loss_ce_dn_1_unscaled": 0.0,
    "test_loss_xy_dn_1_unscaled": 0.0,
    "test_loss_hw_dn_1_unscaled": 0.0,
    "test_cardinality_error_dn_1_unscaled": 0.0,
    "test_loss_ce_2_unscaled": 0.39808743033432703,
    "test_loss_bbox_2_unscaled": 0.10145892096289982,
    "test_loss_giou_2_unscaled": 0.308101641691853,
    "test_loss_xy_2_unscaled": 0.03819054770806665,
    "test_loss_hw_2_unscaled": 0.06326837327330131,
    "test_cardinality_error_2_unscaled": 286.4430909663204,
    "test_loss_bbox_dn_2_unscaled": 0.0,
    "test_loss_giou_dn_2_unscaled": 0.0,
    "test_loss_ce_dn_2_unscaled": 0.0,
    "test_loss_xy_dn_2_unscaled": 0.0,
    "test_loss_hw_dn_2_unscaled": 0.0,
    "test_cardinality_error_dn_2_unscaled": 0.0,
    "test_loss_ce_3_unscaled": 0.4027965914976836,
    "test_loss_bbox_3_unscaled": 0.1007563430474714,
    "test_loss_giou_3_unscaled": 0.30671183139714275,
    "test_loss_xy_3_unscaled": 0.03792145186548582,
    "test_loss_hw_3_unscaled": 0.06283489115662852,
    "test_cardinality_error_3_unscaled": 289.60802644003775,
    "test_loss_bbox_dn_3_unscaled": 0.0,
    "test_loss_giou_dn_3_unscaled": 0.0,
    "test_loss_ce_dn_3_unscaled": 0.0,
    "test_loss_xy_dn_3_unscaled": 0.0,
    "test_loss_hw_dn_3_unscaled": 0.0,
    "test_cardinality_error_dn_3_unscaled": 0.0,
    "test_loss_ce_4_unscaled": 0.3977412321928462,
    "test_loss_bbox_4_unscaled": 0.10067015961539569,
    "test_loss_giou_4_unscaled": 0.30600043201984983,
    "test_loss_xy_4_unscaled": 0.03786034035620414,
    "test_loss_hw_4_unscaled": 0.06280981931222153,
    "test_cardinality_error_4_unscaled": 293.46842933585145,
    "test_loss_bbox_dn_4_unscaled": 0.0,
    "test_loss_giou_dn_4_unscaled": 0.0,
    "test_loss_ce_dn_4_unscaled": 0.0,
    "test_loss_xy_dn_4_unscaled": 0.0,
    "test_loss_hw_dn_4_unscaled": 0.0,
    "test_cardinality_error_dn_4_unscaled": 0.0,
    "test_loss_ce_interm_unscaled": 0.5959718101471598,
    "test_loss_bbox_interm_unscaled": 0.1105376068596471,
    "test_loss_giou_interm_unscaled": 0.31768975278041933,
    "test_loss_xy_interm_unscaled": 0.041415416435413306,
    "test_loss_hw_interm_unscaled": 0.06912219038114144,
    "test_cardinality_error_interm_unscaled": 366.6745042492918,
    "test_coco_eval_bbox": [
      0.015293739501463033,
      0.04427728165861681,
      0.009299968212900021,
      4.8416564440029294e-05,
      0.0036751554426608614,
      0.019192373609019906,
      0.03844243510211014,
      0.08390339120958917,
      0.11544828625392808,
      0.003481240981240981,
      0.030921224638810647,
      0.17249927690536176
    ],
    "test_AP_fire": 0.004161850977330054,
    "test_Recall_fire": 0.056874241811564905,
    "test_AP_smoke": 0.02642562802559601,
    "test_Recall_smoke": 0.1740223306962913,
    "test_mAP50": 0.04427728165861681,
    "best_res": 0.015293739501463033,
    "best_ep": 0,
    "epoch": 0,
    "n_parameters": 18179705,
    "now_time": "2026-04-20 19:45:02.344251",
    "epoch_time": "4:56:43",
    "train_time": 10257.616463661194,
    "val_time": 7545.758574485779
  }
]